README.md
setup.py
src/KCUForms.egg-info/PKG-INFO
src/KCUForms.egg-info/SOURCES.txt
src/KCUForms.egg-info/dependency_links.txt
src/KCUForms.egg-info/requires.txt
src/KCUForms.egg-info/top_level.txt
src/kcuforms/__init__.py
src/kcuforms/errors.py
src/kcuforms/form.py
src/kcuforms/utils.py
src/kcuforms/validators.py
src/kcuforms/fields/__init__.py
src/kcuforms/fields/core.py